docx_mailmerge2-1.0.1.dist-info/licenses/LICENSE.txt
mailmerge/__init__.py
mailmerge/conditional_field.py
mailmerge/constants.py
mailmerge/field.py
mailmerge/mailmerge.py
mailmerge/mergedata.py
mailmerge/mergeoptions.py
mailmerge/part.py
mailmerge/rels.py
mailmerge/unique_man.py
docx_mailmerge2-1.0.1.dist-info/METADATA
docx_mailmerge2-1.0.1.dist-info/WHEEL
docx_mailmerge2-1.0.1.dist-info/top_level.txt
docx_mailmerge2-1.0.1.dist-info/RECORD
