Metadata-Version: 2.4
Name: docx-mailmerge2
Version: 1.0.1
Summary: Performs a Mail Merge on docx (Microsoft Office Word) files
Author-email: Iulian Ciorăscu <ciulian@gmail.com>
License: MIT
Project-URL: Homepage, http://github.com/iulica/docx-mailmerge
Project-URL: Issues, http://github.com/iulica/docx-mailmerge/issues
Keywords: docx,office,openxml,word
Classifier: Development Status :: 5 - Production/Stable
Classifier: Environment :: Console
Classifier: License :: OSI Approved :: MIT License
Classifier: Operating System :: OS Independent
Classifier: Programming Language :: Python
Classifier: Programming Language :: Python :: 3
Classifier: Programming Language :: Python :: 3.7
Classifier: Programming Language :: Python :: 3.8
Classifier: Programming Language :: Python :: 3.9
Classifier: Programming Language :: Python :: 3.10
Classifier: Programming Language :: Python :: 3.11
Classifier: Programming Language :: Python :: 3.12
Classifier: Programming Language :: Python :: 3.13
Classifier: Topic :: Text Processing
Requires-Python: >=3.7
License-File: LICENSE.txt
Requires-Dist: lxml>=3.1.0
Dynamic: license-file
